Torchify/TabularNet.py
Torchify/VisionNet.py
Torchify/__init__.py
torchify-0.4.0.dist-info/LICENSE
torchify-0.4.0.dist-info/METADATA
torchify-0.4.0.dist-info/WHEEL
torchify-0.4.0.dist-info/top_level.txt
torchify-0.4.0.dist-info/RECORD
